pomodoro_timer_cli/__init__.py
pomodoro_timer_cli/__main__.py
pomodoro_timer_cli/complete.wav
pomodoro_timer_cli/pomodoro.py
pomodoro_timer_cli-0.2.0.dist-info/LICENSE
pomodoro_timer_cli-0.2.0.dist-info/METADATA
pomodoro_timer_cli-0.2.0.dist-info/WHEEL
pomodoro_timer_cli-0.2.0.dist-info/entry_points.txt
pomodoro_timer_cli-0.2.0.dist-info/RECORD
